rulesengine/__init__.py
rulesengine/async_client.py
rulesengine/client.py
djungle_rulesengine_client-0.4.0.dist-info/LICENSE
djungle_rulesengine_client-0.4.0.dist-info/METADATA
djungle_rulesengine_client-0.4.0.dist-info/WHEEL
djungle_rulesengine_client-0.4.0.dist-info/top_level.txt
djungle_rulesengine_client-0.4.0.dist-info/RECORD
