Metadata-Version: 2.1
Name: djungle-rulesengine-client
Version: 0.4.0
Summary: A client to Djungle Studio rulesengine API
Home-page: https://github.com/djungle-io/djungle-rulesengine-client
Author: Djungle s.r.l.
License: MIT
Classifier: Environment :: Web Environment
Classifier: Intended Audience :: Developers
Classifier: License :: OSI Approved :: MIT License
Classifier: Operating System :: OS Independent
Classifier: Programming Language :: Python
Classifier: Programming Language :: Python :: 3 :: Only
License-File: LICENSE
Requires-Dist: requests (>=2.30.0)
Requires-Dist: httpx (>=0.24.0)
